Workbook

Sheet AT&T
A1: AT&T INC.
A2: Source
A4: Consolidated Balance Sheets
B5: (dollars in millions, except per share amounts)
A6: at December 31 | C6: 2025 | D6: 2024 | E6: 2023 | I6: 2025 | J6: 2024 | K6: 2023
B7: Assets | H7: Liabilities and Equity
B8: Current assets | H8: Current liabilities
B9: Cash and cash equivalents | C9: 18234 | D9: 3298 | E9: 6722 | H9: Debt maturing within one year | I9: 9011 | J9: 5089 | K9: 9477
B10: Accounts receivable – net of related allowance for credit loss of $429 and $375 | C10: 8843 | D10: 9638 | E10: 10289 | H10: Accounts payable and accrued liabilities | I10: 38514 | J10: 35657 | K10: 35852
B11: Inventories | C11: 2420 | D11: 2270 | E11: 2177 | H11: Advanced billings and customer deposits | I11: 4266 | J11: 4099 | K11: 3778
B12: Prepaid and other current assets | C12: 19235 | D12: 15962 | E12: 17270 | H12: Dividends payable | I12: 1989 | J12: 2027 | K12: 2020
B13: Total current assets | C13: 48732 | D13: 31168 | E13: 36458 | H13: Total current liabilities | I13: 53780 | J13: 46872 | K13: 51127
B15: Property, plant and equipment - net | C15: 131559 | D15: 128871 | E15: 128489 | H15: Long-term debt | I15: 127089 | J15: 118443 | K15: 127854
B16: Goodwill - Net | C16: 63425 | D16: 63432 | E16: 67854 | H16: Noncurrent deferred taxes liabilities | I16: 58312 | J16: 58939 | K16: 58666
B17: Licenses - Net | C17: 128148 | D17: 127035 | E17: 127219 | H17: Postemployment benefit obligations | I17: 8478 | J17: 9025 | K17: 8734
B18: Other intangible assets, net | C18: 5254 | D18: 5255 | E18: 5283 | H18: Non-current operating lease liabilities | I18: 18943 | J18: 17391 | K18: 17568
B19: Investments in and Advances to Equity Affiliates | C19: 1106 | D19: 295 | E19: 1251 | H19: Other noncurrent liabilities | I19: 25104 | J19: 23900 | K19: 23696
B20: Operating lease right-of-use assets | C20: 22642 | D20: 20909 | E20: 20905 | H20: Total deferred credits and other noncurrent liabilities | I20: 110837 | J20: 109255 | K20: 108664
B21: Other assets | C21: 19332 | D21: 17830 | E21: 19601 | H21: Redeemable Noncontrolling Interst | I21: 2001 | J21: 1980
B22: Total assets | C22: 420198 | D22: 394795 | E22: 407060 | H22: Total Liabilities | I22: =I13+I15+I20+I21 -> 293707 | J22: =J13+J15+J20+J21 -> 276550 | K22: =K13+K15+K20+K21 -> 287645
H23: Stockholders` Equity
H24: Preferred stock ($1 par value, 10,000,000 authorized at December 31, 2025 and December 31, 2024): | I24: 0 | J24: 0 | K24: 0
H25: Common stock ($1 par value, 14,000,000,000 authorized at December 31, 2025 and December 31, 2024: issued 7,620,748,598 at December 31, 2025 and December 31, 2024) | I25: 7621 | J25: 7621 | K25: 7621
H26: Additional paid-in capital | I26: 106533 | J26: 109108 | K26: 114519
H27: Retained earnings | I27: 15768 | J27: 1871 | K27: -5015
H28: Treasury stock (583,246,242 at December 31, 2025 and 444,853,148 at December 31, 2024, at cost) | I28: -18529 | J28: -15023 | K28: -16128
H29: Accumulated other comprehensive income (loss) | I29: -860 | J29: 795 | K29: 2300
H30: Noncontrolling interest | I30: 15958 | J30: 13873 | K30: 14145
H31: Total stockholders' equity | I31: 126491 | J31: 118245 | K31: 117442
H32: Total Liabilities and Stockholders' Equity | I32: 420198 | J32: 394795 | K32: 407060
A34: Consolidated Statements of Income | C34: (dollars in millions, except per share amounts) | H34: Consolidated Statements of Cash Flows | I34: (dollars in millions, except per share amounts)
A35: at December 31 | C35: 2025 | D35: 2024 | E35: 2023 | H35: at December 31 | I35: 2025 | J35: 2024 | K35: 2023
B36: Operating Revenues | H36: Operating Activities
B37: Service | C37: 101158 | D37: 100135 | E37: 99649 | H37: Net Income | I37: 23386 | J37: 12253 | K37: 15623
B38: Equipment | C38: 24490 | D38: 22201 | E38: 22779 | H38: Adjustments to reconcile net income to net cash provided by
B39: Total operating revenues | C39: 125648 | D39: 122336 | E39: 122428 | H39: operating activities:
H40: Depreciation and amortization | I40: 20886 | J40: 20580 | K40: 18777
B41: Operating Expenses | H41: Provision for uncollectible accounts | I41: 2271 | J41: 1969 | K41: 1969
B42: Cost of revenues | H42: Asset impairments and abandonments and restructuring | I42: 838 | J42: 5075 | K42: 1193
B43: Equipment | C43: 25396 | D43: 22249 | E43: 23136 | H43: Pension and postretirement benefit expense (credit) | I43: -1588 | J43: -1883 | K43: -2552
B44: Other cost of revenues (exclusive of depreciation and amortization shown separately below) | C44: 25424 | D44: 26972 | E44: 26987 | H44: Actuarial and settlement (gain) loss on pension and
B45: Selling, general and administrative | C45: 28942 | D45: 28411 | E45: 28874 | H45: postretirement benefits - net | I45: 519 | J45: 56 | K45: 1594
B46: Asset impairments and abandonments and restructuring | C46: 838 | D46: 5075 | E46: 1193 | H46: Net (gain) loss on investments | I46: -5889 | J46: 80 | K46: 441
B47: Depreciation and amortization | C47: 20886 | D47: 20580 | E47: 18777 | H47: Changes in operating assets and liabilities:
B48: Total operating expenses | C48: 101486 | D48: 103287 | E48: 98967 | H48: Receivables | I48: -1526 | J48: 123 | K48: 82
H49: Equipment installment receivables and related sales | I49: 324 | J49: -1846 | K49: -133
B50: Operating Income | C50: 24162 | D50: 19049 | E50: 23461 | H50: Contract asset and cost deferral | I50: -1208 | J50: 160 | K50: -1006
B51: Other Income (Expense) Interest expense | C51: -6804 | D51: -6759 | E51: -6704 | H51: Inventories, prepaid and other current assets | I51: -460 | J51: 70 | K51: 747
B52: Equity in net income of affiliates | C52: 1895 | D52: 1989 | E52: 1675 | H52: Accounts payable and other accrued liabilities | I52: 884 | J52: -1104 | K52: -1574
B53: Other income (expense) - net | C53: 7754 | D53: 2419 | E53: 1416 | H53: Changes in income taxes | I53: 2226 | J53: 1978 | K53: 2618
B54: Total other income (expense) | C54: 2845 | D54: -2351 | E54: -3613 | H54: Postretirement claims and contributions | I54: -1436 | J54: -166 | K54: -735
B55: Income Before Income Taxes | C55: 27007 | D55: 16698 | E55: 19848 | H55: Other - net | I55: 1057 | J55: 1426 | K55: 1270
B56: Income tax expense | C56: 3621 | D56: 4445 | E56: 4225 | H56: Total adjustments | I56: 16898 | J56: 26518 | K56: 22691
H57: Net Cash Provided by Operating Activities | I57: 40284 | J57: 38771 | K57: 38314
B58: Net Income | C58: 23386 | D58: 12253 | E58: 15623 | H58: Investing Activities
B59: Less: Net Income Attributable to Noncontrolling Interest | C59: -1433 | D59: -1305 | E59: -1223 | H59: Capital expenditures | I59: -20842 | J59: -20263 | K59: -17853
B60: Net Income Attributable to AT&T | C60: 21953 | D60: 10948 | E60: 14400 | H60: Acquisitions, net of cash acquired | I60: -379 | J60: -380 | K60: -2942
H61: Dispositions | I61: 3218 | J61: 75 | K61: 72
B62: Less: Preferred Stock Dividends and Redemption Gain | C62: -64 | D62: -202 | E62: -208 | H62: Distributions from DIRECTV in excess of cumulative equity in
B63: Net Income Attributable to Common Stock | C63: 21889 | D63: 10746 | E63: 14192 | H63: earnings | I63: 0 | J63: 928 | K63: 2049
H64: (Purchases), sales and settlements of securities - net | I64: 181 | J64: 2575 | K64: -902
B65: Basic Earnings Per Share Attributable to Common Stock | C65: 3.04 | D65: 1.49 | E65: 1.97 | H65: Other - net | I65: -955 | J65: -425 | K65: -84
B67: Diluted Earnings Per Share Attributable to Common Stock | C67: 3.04 | D67: 1.49 | E67: 1.97 | H67: Net Cash Used in Investing Activities | I67: -18777 | J67: -17490 | K67: -19660
H68: Financing Activities
H69: Net change in short-term borrowings with original maturities of
H70: three months or less | I70: 0 | J70: 0 | K70: -914
H71: Issuance of other short-term borrowings | I71: 0 | J71: 491 | K71: 5406
H72: Repayment of other short-term borrowings | I72: 0 | J72: -2487 | K72: -3415
H73: Issuance of long-term debt | I73: 14027 | J73: 19 | K73: 10004
H74: Repayment of long-term debt | I74: -5528 | J74: -10297 | K74: -12044
H75: Note payable to DIRECTV, net of payments | I75: 0 | J75: 0 | K75: -130
H76: Payment of vendor financing | I76: -1181 | J76: -1792 | K76: -5742
H78: Redemption of preferred stock | I78: -2075 | J78: 0 | K78: 0
H79: Purchase of treasury stock | I79: -4500 | J79: -215 | K79: -194
H80: Issuance of treasury stock | I80: 21 | J80: 15 | K80: 3
H81: Issuance of preferred interests in subsidiary | I81: 2221 | J81: 0 | K81: 7151
H82: Redemption of preferred interests in subsidiary | I82: -65 | J82: 0 | K82: -5333
... H85: Net Cash Used in Financing Activities | I85: -6386 | J85: -24708 | K85: -15614
H87: Net increase (decrease) in cash and cash equivalents and
H88: restricted cash | I88: 15121 | J88: -3427 | K88: 3040
H89: Cash and cash equivalents and restricted cash beginning of year | I89: 3406 | J89: 6833 | K89: 3793
H90: Cash and Cash Equivalents and Restricted Cash End of Year | I90: 18527 | J90: 3406 | K90: 6833
H92: Free cash flow from operations | I92: =I57+I59 -> 19442 | J92: =J57+J59 -> 18508 | K92: =K57+K59 -> 20461

Sheet T-mobile
A1: T-mobile US, Inc.
A2: Source
A4: Consolidated Balance Sheets
B5: (dollars in millions, except per share amounts)
A6: at December 31 | C6: 2025 | D6: 2024 | E6: 2023 | I6: 2025 | J6: 2024 | K6: 2023
B7: Assets | H7: Liabilities and Stockholders' Equity
B8: Current assets | H8: Current liabilities
B9: Cash and cash equivalents | C9: 5598 | D9: 5409 | E9: 5135 | H9: Accounts payable and accrued liabilities | I9: 10280 | J9: 8463 | K9: 10373
B10: Accounts receivable, net of allowance for credit losses of $226 and $176 | C10: 4874 | D10: 4276 | E10: 4692 | H10: Short-term debt | I10: 5135 | J10: 4068 | K10: 3619
B11: Equipment installment plan receivables, net of allowance for credit losses and imputed discount of $733 and $656 | C11: 4997 | D11: 4379 | E11: 4456 | H11: Deferred revenue | I11: 1533 | J11: 1222 | K11: 825
B12: Inventory | C12: 2405 | D12: 1607 | E12: 1678 | H12: Short-term operating lease liabilities | I12: 3814 | J12: 3281 | K12: 3555
B13: Prepaid expenses | C13: 1215 | D13: 880 | E13: 702 | H13: Short-term financing lease liabilities | I13: 1163 | J13: 1175 | K13: 1260
B14: Other current assets | C14: 5372 | D14: 1853 | E14: 2352 | H14: Other current liabilities | I14: 2575 | J14: 1965 | K14: 1296
B15: Total current assets | C15: 24461 | D15: 18404 | E15: 19015 | H15: Total current liabilities | I15: 24500 | J15: 20174 | K15: 20928
B16: Property and equipment, net | C16: 38333 | D16: 38533 | E16: 40432 | H16: Long-term debt | I16: 79649 | J16: 72700 | K16: 69903
B17: Operating lease right-of-use assets | C17: 25692 | D17: 25398 | E17: 27135 | H17: Long-term debt to affiliates | I17: 1498 | J17: 1497 | K17: 1496
B18: Financing lease right-of-use assets | C18: 2760 | D18: 3091 | E18: 3270 | H18: Tower obligations | I18: 3532 | J18: 3664 | K18: 3777
B19: Goodwill | C19: 13678 | D19: 13005 | E19: 12234 | H19: Deferred tax liabilities | I19: 19583 | J19: 16700 | K19: 13458
B20: Spectrum licenses | C20: 98032 | D20: 100558 | E20: 96707 | H20: Operating lease liabilities | I20: 26371 | J20: 26408 | K20: 28240
B21: Other intangible assets, net | C21: 3843 | D21: 2512 | E21: 2618 | H21: Financing lease liabilities | I21: 1107 | J21: 1151 | K21: 1236
B22: Equipment installment plan receivables due after one year, net of | H22: Other long-term liabilities | I22: 3794 | J22: 4000 | K22: 3929
B23: allowance for credit losses and imputed discount of $213 and $158 | C23: 2683 | D23: 2209 | E23: 2042 | H23: Total long-term liabilities | I23: 135534 | J23: 126120 | K23: 122039
B24: Other assets | C24: 9755 | D24: 4325 | E24: 4229 | H24: Total Liabilities | I24: =I23+I15 -> 160034 | J24: =J23+J15 -> 146294 | K24: =K23+K15 -> 142967
B25: Total assets | C25: 219237 | D25: 208035 | E25: 207682 | H25: Stockholders' equity
H26: Common stock, par value $0.00001 per share, 2,000,000,000 shares
H27: authorized; 1,275,774,235 and 1,271,074,364 shares issued,
H28: 1,106,930,661 and 1,144,579,681 shares outstanding | I28: 0 | J28: 0 | K28: 0
H29: Additional paid-in capital | I29: 69460 | J29: 68798 | K29: 67705
H30: Treasury stock, at cost, 168,843,574 and 126,494,683 shares | I30: -30545 | J30: -20584 | K30: -9373
H31: Accumulated other comprehensive loss | I31: -848 | J31: -857 | K31: -964
H32: Retained earnings | I32: 21136 | J32: 14384 | K32: 7347
H33: Total stockholders' equity | I33: 59203 | J33: 61741 | K33: 64715
H34: Total liabilities and stockholders' equity | I34: 219237 | J34: 208035 | K34: 207682
A36: Consolidated Statements of Income | C36: (dollars in millions, except per share amounts) | H36: Consolidated Statements of Cash Flows | I36: (dollars in millions, except per share amounts)
A37: at December 31 | C37: 2025 | D37: 2024 | E37: 2023 | H37: at December 31 | I37: 2025 | J37: 2024 | K37: 2023
B38: Revenues | H38: Operating activities
B39: Postpaid revenues | C39: 57932 | D39: 52340 | E39: 48692
B40: Prepaid revenues | C40: 10497 | D40: 10399 | E40: 9767 | H40: Net income | I40: 10992 | J40: 11339 | K40: 8317
B41: Wholesale and other service revenues | C41: 2877 | D41: 3439 | E41: 4782 | H41: Adjustments to reconcile net income to net cash provided
B42: Total service revenues | C42: 71306 | D42: 66178 | E42: 63241 | H42: by operating activities
B43: Equipment revenues | C43: 15972 | D43: 14263 | E43: 14138 | H43: Depreciation and amortization | I43: 13508 | J43: 12919 | K43: 12818
B44: Other revenues | C44: 1031 | D44: 959 | E44: 1179 | H44: Stock-based compensation expense | I44: 829 | J44: 649 | K44: 667
B45: Total revenues | C45: 88309 | D45: 81400 | E45: 78558 | H45: Deferred income tax expense | I45: 2864 | J45: 3120 | K45: 2600
H46: Bad debt expense | I46: 1370 | J46: 1192 | K46: 898
B47: Operating expenses | H47: Losses from sales of receivables | I47: 58 | J47: 62 | K47: 165
B48: Cost of services, exclusive of depreciation and amortization shown separately below | C48: 11497 | D48: 10771 | E48: 11655
B49: Cost of equipment sales, exclusive of depreciation and amortization shown separately below | C49: 21277 | D49: 18882 | E49: 18533 | H49: Impairment expense | I49: 278 | J49: 0 | K49: 0
B50: Selling, general and administrative | C50: 23470 | D50: 20818 | E50: 21311 | H50: Loss on remeasurement of disposal group held for sale | I50: 0 | J50: 0 | K50: 9
B51: Gain on disposal group held for sale | C51: 0 | D51: 0 | E51: -25 | H51: Changes in operating assets and liabilities
B52: Impairment expense | C52: 278 | D52: 0 | E52: 0 | H52: Accounts receivable | I52: -755 | J52: -3088 | K52: -5038
B53: Depreciation and amortization | C53: 13508 | D53: 12919 | E53: 12818 | H53: Equipment installment plan receivables | I53: -877 | J53: -523 | K53: 170
B54: Total operating expenses | C54: 70030 | D54: 63390 | E54: 64292 | H54: Inventory | I54: -615 | J54: 131 | K54: 197
B55: Operating income | C55: 18279 | D55: 18010 | E55: 14266 | H55: Operating lease right-of-use assets | I55: 3635 | J55: 3480 | K55: 3721
B56: Other expense, net | H56: Other current and long-term assets | I56: -1488 | J56: -411 | K56: -358
B57: Interest expense, net | C57: -3774 | D57: -3411 | E57: -3335 | H57: Accounts payable and accrued liabilities | I57: 1542 | J57: -2041 | K57: -1126
B58: Other (expense) income, net | C58: -224 | D58: 113 | E58: 68 | H58: Short- and long-term operating lease liabilities | I58: -3457 | J58: -3879 | K58: -3785
B59: Total other expense, net | C59: -3998 | D59: -3298 | E59: -3267 | H59: Other current and long-term liabilities | I59: -379 | J59: -678 | K59: -839
B60: Income before income taxes | C60: 14281 | D60: 14712 | E60: 10999 | H60: Other, net | I60: 445 | J60: 21 | K60: 143
B61: Income tax expense | C61: -3289 | D61: -3373 | E61: -2682 | H61: Net cash provided by operating activities | I61: 27950 | J61: 22293 | K61: 18559
B62: Net income | C62: 10992 | D62: 11339 | E62: 8317
H63: Investing activities
B64: Net income | C64: 10992 | D64: 11339 | E64: 8317 | H64: Purchases of property and equipment, including capitalized interest of $(43), $(34) and $(104) | I64: -9955 | J64: -8840 | K64: -9801
B65: Other comprehensive income, net of tax | H65: Purchases of spectrum licenses and other intangible
B66: Reclassification of loss from cash flow hedges, net of | H66: assets, including deposits | I66: -2568 | J66: -3471 | K66: -1010
B67: tax effect of $65, $60 and $56 | C67: 190 | D67: 176 | E67: 163 | H67: Proceeds from the sale of property, equipment and
B68: (Losses) gains on fair value hedges, net of tax effect | H68: intangible assets | I68: 2168 | J68: 99 | K68: 153
B69: of $(64), $5 and $0 | C69: -187 | D69: 16 | E69: 0 | H69: Proceeds from sales of tower sites | I69: 0 | J69: 0 | K69: 12
B70: Unrealized (loss) gain on foreign currency translation | H70: Proceeds related to beneficial interests in | I70: 0 | J70: 3579 | K70: 4816
B71: adjustment, net of tax effect of $0, $0 and $0 | C71: -1 | D71: 0 | E71: 9 | H71: securitization transactions
B72: Actuarial gain (loss), net of amortization and
B73: reclassification, on pension and other postretirement | H73: Acquisition of companies, net of cash acquired | I73: -3523 | J73: -373 | K73: 0
B74: benefits, net of tax effect of $2, $(29) and $(31) | C74: 7 | D74: -85 | E74: -90
H75: Investments in unconsolidated affiliates, net | I75: -4056 | J75: -18 | K75: -7
B76: Other comprehensive income | C76: 9 | D76: 107 | E76: 82 | H76: Other, net | I76: 327 | J76: -48 | K76: 8
B77: Total comprehensive income | C77: 11001 | D77: 11446 | E77: 8399
B78: Earnings per share | H78: Net cash used in investing activities | I78: -17607 | J78: -9072 | K78: -5829
B79: Basic | C79: 9.75 | D79: 9.7 | E79: 7.02 | H79: Financing activities
B80: Diluted | C80: 9.72 | D80: 9.66 | E80: 6.93
B81: Weighted-average shares outstanding in millions | H81: Proceeds from issuance of long-term debt, net | I81: 12010 | J81: 8587 | K81: 8446
B82: Basic | C82: =1127984348/1000000 -> 1127.9843 | D82: =1169195373/1000000 -> 1169.1954 | E82: =1185121562/1000000 -> 1185.1216 | H82: Repayments of financing lease obligations | I82: -1252 | J82: -1367 | K82: -1227
B83: Diluted | C83: =1131076251/1000000 -> 1131.0763 | D83: =1173213898/1000000 -> 1173.2139 | E83: =1200286264/1000000 -> 1200.2863 | H83: Repayments of long-term debt | I83: -6199 | J83: -5073 | K83: -5051
H84: Repurchases of common stock | I84: -9974 | J84: -11228 | K84: -13074
H85: Dividends on common stock | I85: -4121 | J85: -3300 | K85: -747
H86: Tax withholdings on share-based awards | I86: -434 | J86: -269 | K86: -297
H87: Other, net | I87: -111 | J87: -165 | K87: -147
H89: Net cash used in financing activities | I89: -10081 | J89: -12815 | K89: -12097
H90: Effect of exchange rate changes on cash and cash | J90: 0 | K90: 0
H91: equivalents, including restricted cash | I91: 1
H92: Change in cash and cash equivalents, including
H93: restricted cash | I93: 263 | J93: 406 | K93: 633
H94: Cash and cash equivalents, including restricted cash
H95: Beginning of period | I95: 5713 | J95: 5307 | K95: 4674
H96: End of period | I96: 5976 | J96: 5713 | K96: 5307
H98: Free cash flow from operations | I98: =I61+'T-mobile'!I64 -> 17995 | J98: =J61+'T-mobile'!J64 -> 13453 | K98: =K61+'T-mobile'!K64 -> 8758

Sheet Verizon Com
A1: Verizon Communications Inc. and Subsidiaries
A2: Source
A4: Consolidated Balance Sheets
B5: (dollars in millions, except per share amounts)
A6: at December 31 | C6: 2025 | D6: 2024 | E6: 2023 | I6: 2025 | J6: 2024 | K6: 2023
B7: Assets | H7: Liabilities and Equity
B8: Current assets | H8: Current liabilities
B9: Cash and cash equivalents | C9: 19048 | D9: 4194 | E9: 2065 | H9: Debt maturing within one year | I9: 18618 | J9: 22633 | K9: 12973
B10: Accounts receivable | C10: 28347 | D10: 27261 | E10: 26102 | H10: Accounts payable and accrued liabilities | I10: 24981 | J10: 23374 | K10: 23453
B11: Less Allowance for credit losses | C11: -1250 | D11: -1152 | E11: -1017 | H11: Current operating lease liabilities | I11: 4542 | J11: 4415 | K11: 4266
B12: Accounts receivable, net | C12: 27097 | D12: 26109 | E12: 25085 | H12: Other current liabilities | I12: 14229 | J12: 14349 | K12: 12531
B13: Inventories | C13: 2441 | D13: 2247 | E13: 2057 | H13: Total current liabilities | I13: 62370 | J13: 64771 | K13: 53223
B14: Prepaid expenses and other | C14: 8336 | D14: 7973 | E14: 7607
B15: Total current assets | C15: 56922 | D15: 40523 | E15: 36814 | H15: Long-term debt | I15: 139532 | J15: 121381 | K15: 137701
H16: Employee benefit obligations | I16: 11099 | J16: 11997 | K16: 13189
B17: Property, plant and equipment | C17: 337991 | D17: 331406 | E17: 320108 | H17: Deferred income taxes | I17: 48717 | J17: 46732 | K17: 45781
B18: Less Accumulated depreciation | C18: 228524 | D18: 222884 | E18: 211798 | H18: Non-current operating lease liabilities | I18: 18951 | J18: 19928 | K18: 20002
B19: Property, plant and equipment, net | C19: 109467 | D19: 108522 | E19: 108310 | H19: Other liabilities | I19: 17848 | J19: 19327 | K19: 16560
H20: Total long-term liabilities | I20: 236147 | J20: 219365 | K20: 233233
B21: Investments in unconsolidated businesses | C21: 785 | D21: 842 | E21: 953
B22: Wireless licenses | C22: 157039 | D22: 156613 | E22: 155667 | H22: Equity
B23: Goodwill | C23: 22841 | D23: 22841 | E23: 22843 | H23: Series preferred stock ($0.10 par value; 250,000,000 shares authorized; none issued) | I23: 0 | J23: 0 | K23: 0
B24: Other intangible assets, net | C24: 10458 | D24: 11129 | E24: 11057 | H24: Common stock ($0.10 par value; 6,250,000,000 shares authorized in each period; 4,291,433,646 shares issued in each period) | I24: 429 | J24: 429 | K24: 429
B25: Operating lease right-of-use assets | C25: 23498 | D25: 24472 | E25: 24726 | H25: Additional paid in capital | I25: 13372 | J25: 13466 | K25: 13631
B26: Other assets | C26: 23248 | D26: 19769 | E26: 19885 | H26: Retained earnings | I26: 94744 | J26: 89110 | K26: 82915
B27: Total assets | C27: 404258 | D27: 384711 | E27: 380255 | H27: Accumulated other comprehensive loss | I27: -1727 | J27: -923 | K27: -1380
H28: Common stock in treasury, at cost | I28: -3255 | J28: -3583 | K28: -3821
H29: Deferred compensation – ESOPs and other | I29: 897 | J29: 738 | K29: 656
H30: Noncontrolling interests | I30: 1281 | J30: 1338 | K30: 1369
H31: Total equity | I31: 105741 | J31: 100575 | K31: 93799
H32: Total liabilities and equity | I32: 404258 | J32: 384711 | K32: 380255
A34: Consolidated Statements of Income | C34: (dollars in millions, except per share amounts) | H34: Consolidated Statements of Cash Flows | I34: (dollars in millions, except per share amounts)
A35: at December 31 | C35: 2025 | D35: 2024 | E35: 2023 | H35: at December 31 | I35: 2025 | J35: 2024 | K35: 2023
B36: Operating Revenues | H36: Cash Flows from Operating Activities
B37: Service revenues and other | C37: 112721 | D37: 111571 | E37: 109652 | H37: Net Income | I37: 17608 | J37: 17949 | K37: 12095
B38: Wireless equipment revenues | C38: 25470 | D38: 23217 | E38: 24322 | H38: Adjustments to reconcile net income to net cash provided by operating activities:
B39: Total Operating Revenues | C39: 138191 | D39: 134788 | E39: 133974 | H39: Depreciation and amortization expense | I39: 18349 | J39: 17892 | K39: 17624
H40: Employee retirement benefits | I40: 1025 | J40: -52 | K40: 1206
B41: Operating Expenses | H41: Deferred income taxes | I41: 2340 | J41: 815 | K41: 2388
B42: Cost of services (exclusive of items shown below) | C42: 27789 | D42: 27997 | E42: 28100 | H42: Provision for expected credit losses | I42: 2349 | J42: 2338 | K42: 2214
B43: Cost of wireless equipment | C43: 28976 | D43: 26100 | E43: 26787 | H43: Equity in losses of unconsolidated businesses | I43: 42 | J43: 75 | K43: 84
B44: Selling, general and administrative expense | C44: 33818 | D44: 34113 | E44: 32745 | H44: Verizon Business Group goodwill impairment | I44: 0 | J44: 0 | K44: 5841
B45: Depreciation and amortization expense | C45: 18349 | D45: 17892 | E45: 17624 | H45: Changes in current assets and liabilities, net of effects from acquisition/disposition of businesses:
B46: Verizon Business Group goodwill impairment | C46: 0 | D46: 0 | E46: 5841 | H46: Accounts receivable | I46: -2513 | J46: -2565 | K46: -2198
B47: Total Operating Expenses | C47: 108932 | D47: 106102 | E47: 111097 | H47: Inventories | I47: -232 | J47: -196 | K47: 287
H48: Prepaid expenses and other | I48: -1394 | J48: -626 | K48: -435
B49: Operating Income | C49: 29259 | D49: 28686 | E49: 22877 | H49: Accounts payable and accrued liabilities | I49: 1819 | J49: 1109 | K49: 2079
B50: Equity in earnings (losses) of unconsolidated businesses | C50: 0 | D50: -53 | E50: -53 | H50: Other, net | I50: -2256 | J50: 173 | K50: -3710
B51: Other income (expense), net | C51: 107 | D51: 995 | E51: -313 | H51: Net cash provided by operating activities | I51: 37137 | J51: 36912 | K51: 37475
B52: Interest expense | C52: -6694 | D52: -6649 | E52: -5524
B53: Income Before Provision For Income Taxes | C53: 22672 | D53: 22979 | E53: 16987 | H53: Cash Flows from Investing Activities
B54: Provision for income taxes | C54: -5064 | D54: -5030 | E54: -4892 | H54: Capital expenditures | I54: -17011 | J54: -17090 | K54: -18767
B55: Net Income | C55: 17608 | D55: 17949 | E55: 12095 | H55: Acquisitions of businesses, net of cash acquired | I55: 0 | J55: 0 | K55: -30
H56: Acquisitions of wireless licenses | I56: -450 | J56: -900 | K56: -5796
B57: Net income attributable to noncontrolling interests | C57: 434 | D57: 443 | E57: 481 | H57: Other, net | I57: 801 | J57: -684 | K57: 1161
B58: Net income attributable to Verizon | C58: 17174 | D58: 17506 | E58: 11614 | H58: Net cash used in investing activities | I58: -16660 | J58: -18674 | K58: -23432
B59: Net Income (Total) | C59: 17608 | D59: 17949 | E59: 12095
H60: Cash Flows from Financing Activities
A61: only current shares | B61: Basic Earnings Per Common Share | H61: Proceeds from long-term borrowings | I61: 18268 | J61: 3146 | K61: 2018
B62: Net income attributable to Verizon | C62: 4.06 | D62: 4.15 | E62: 2.76 | H62: Proceeds from asset-backed borrowings | I62: 9338 | J62: 12422 | K62: 6594
B63: Weighted-average shares outstanding (in millions) | C63: 4226 | D63: 4218 | E63: 4211 | H63: Repayments of long-term borrowings | I63: -11352 | J63: -11854 | K63: -6181
H64: Repayments of asset-backed borrowings | I64: -8437 | J64: -8490 | K64: -4443
A65: all and possible future shares | B65: Diluted Earnings Per Common Share | H65: Dividends paid | I65: -11481 | J65: -11249 | K65: -11025
B66: Net income attributable to Verizon | C66: 4.06 | D66: 4.14 | E66: 2.75 | H66: Other, net | I66: -1949 | J66: -1075 | K66: -1620
B67: Weighted-average shares outstanding (in millions) | C67: 4231 | D67: 4223 | E67: 4215 | H67: Net cash used in financing activities | I67: -5613 | J67: -17100 | K67: -14657
H69: Increase (decrease) in cash, cash equivalents and restricted cash | I69: 14864 | J69: 1138 | K69: -614
H70: Cash, cash equivalents and restricted cash, beginning of period | I70: 4635 | J70: 3497 | K70: 4111
H71: Cash, cash equivalents and restricted cash, end of period (Note 1) | I71: 19499 | J71: 4635 | K71: 3497
H73: Free cash flow from operations | I73: =I51+I54 -> 20126 | J73: =J51+J54 -> 19822 | K73: =K51+K54 -> 18708

Sheet Financial Ratios
B1: RAVSHANBEK MAMASAIDOV
B3: Verizon Communications Inc. and Subsidiaries | J3: Financial Ratios Comparison (31 December, 2025)
B4: Financial Ratios | C4: Formulas | D4: 2025 | E4: 2024 | F4: 2023 | K4: Verizon | L4: AT&T | M4: T-mobile
B5: Liquidity Ratios (Short-Term Solvency) | J5: Current Ratio | K5: =VLOOKUP(J5,B6:F26,3,FALSE) -> 0.91265031 | L5: =VLOOKUP(J5,B34:F55,3,FALSE) -> 0.90613611 | M5: =VLOOKUP(J5,B59:F79,3,FALSE) -> 0.99840816
B6: Current Ratio | C6: Current_Assets / Current_Liabilities | D6: ='Verizon Com'!C15/'Verizon Com'!I13 -> 0.91265031 | E6: ='Verizon Com'!D15/'Verizon Com'!J13 -> 0.62563493 | F6: ='Verizon Com'!E15/'Verizon Com'!K13 -> 0.69169344 | J6: Quick Ratio | K6: =VLOOKUP(J6,B7:F27,3,FALSE) -> 0.87351291 | L6: =VLOOKUP(J6,B35:F56,3,FALSE) -> 0.86113797 | M6: =VLOOKUP(J6,B60:F80,3,FALSE) -> 0.9002449
B7: Quick Ratio | C7: (Current_Assets - Inventory) / Current_Liabilities | D7: =('Verizon Com'!C15-'Verizon Com'!C13)/'Verizon Com'!I13 -> 0.87351291 | E7: =('Verizon Com'!D15-'Verizon Com'!D13)/'Verizon Com'!J13 -> 0.59094348 | F7: =('Verizon Com'!E15-'Verizon Com'!E13)/'Verizon Com'!K13 -> 0.65304474 | J7: Cash Ratio | K7: =VLOOKUP(J7,B8:F28,3,FALSE) -> 0.30540324 | L7: =VLOOKUP(J7,B36:F57,3,FALSE) -> 0.33904797 | M7: =VLOOKUP(J7,B61:F81,3,FALSE) -> 0.2284898
B8: Cash Ratio | C8: Cash / Current Liabilities | D8: ='Verizon Com'!C9/'Verizon Com'!I13 -> 0.30540324 | E8: ='Verizon Com'!D9/'Verizon Com'!J13 -> 0.0647512 | F8: ='Verizon Com'!E9/'Verizon Com'!K13 -> 0.038799015 | J8: Debt to Equity Ratio | K8: =VLOOKUP(J8,B9:F29,3,FALSE) -> 2.8230961 | L8: =VLOOKUP(J8,B37:F58,3,FALSE) -> 2.3219597 | M8: =VLOOKUP(J8,B62:F82,3,FALSE) -> 2.70314
B9: Long-Term Solvency | J9: Debt to Assets Ratio | K9: =VLOOKUP(J9,B10:F30,3,FALSE) -> 0.73843189 | L9: =VLOOKUP(J9,B38:F59,3,FALSE) -> 0.69897287 | M9: =VLOOKUP(J9,B63:F83,3,FALSE) -> 0.7299589
B10: Debt to Equity Ratio | C10: Total_Liabilities / Shareholders_Equity | D10: =('Verizon Com'!I13+'Verizon Com'!I20)/'Verizon Com'!I31 -> 2.8230961 | E10: =('Verizon Com'!J13+'Verizon Com'!J20)/'Verizon Com'!J31 -> 2.8251156 | F10: =('Verizon Com'!K13+'Verizon Com'!K20)/'Verizon Com'!K31 -> 3.0539345 | J10: Interest Coverage | K10: =VLOOKUP(J10,B11:F31,3,FALSE) -> 4.3709292 | L10: =VLOOKUP(J10,B39:F60,3,FALSE) -> 3.5511464 | M10: =VLOOKUP(J10,B64:F84,3,FALSE) -> 4.8434022
B11: Debt to Assets Ratio | C11: Total_Liabilities / Total Assets | D11: =('Verizon Com'!I13+'Verizon Com'!I20)/'Verizon Com'!C27 -> 0.73843189 | E11: =('Verizon Com'!J13+'Verizon Com'!J20)/'Verizon Com'!D27 -> 0.73856999 | F11: =('Verizon Com'!K13+'Verizon Com'!K20)/'Verizon Com'!E27 -> 0.75332606
B12: Interest Coverage | C12: Operating_Income / Interest_Expense | D12: =-'Verizon Com'!C49/'Verizon Com'!C52 -> 4.3709292 | E12: =-'Verizon Com'!D49/'Verizon Com'!D52 -> 4.314333 | F12: =-'Verizon Com'!E49/'Verizon Com'!E52 -> 4.1413831 | J12: Total Asset Turnover | K12: =VLOOKUP(J12,B12:F32,3,FALSE) -> 0.34183863 | L12: =VLOOKUP(J12,B40:F61,3,FALSE) -> 0.29902094 | M12: =VLOOKUP(J12,B66:F86,3,FALSE) -> 0.40280153
B13: Efficiency Ratios | J13: Accounts Receivables Turnover | K13: =VLOOKUP(J13,B13:F33,3,FALSE) -> 71.570544 | L13: =VLOOKUP(J13,B41:F62,3,FALSE) -> 25.688391 | M13: =VLOOKUP(J13,B67:F87,3,FALSE) -> 20.145285
B14: Total Asset Turnover | C14: Revenue / Total_Assets | D14: ='Verizon Com'!C39/'Verizon Com'!C27 -> 0.34183863 | E14: ='Verizon Com'!D39/'Verizon Com'!D27 -> 0.3503617 | F14: ='Verizon Com'!E39/'Verizon Com'!E27 -> 0.35232673 | J14: Inventory Turnover | K14: =VLOOKUP(J14,B14:F34,3,FALSE) -> 15.695675 | L14: =VLOOKUP(J14,B42:F63,3,FALSE) -> 17.380952 | M14: =VLOOKUP(J14,B68:F88,3,FALSE) -> 26.784189
B15: Accounts Receivables Turnover | C15: Revenue / Accounts_Receivable | D15: =365/('Verizon Com'!C39/'Verizon Com'!C12) -> 71.570544 | E15: =365/('Verizon Com'!D39/'Verizon Com'!D12) -> 70.702028 | F15: =365/('Verizon Com'!E39/'Verizon Com'!E12) -> 68.341805 | J15: Accounts Payables turnover | K15: =VLOOKUP(J15,B15:F35,3,FALSE) -> 160.62829 | L15: =VLOOKUP(J15,B43:F64,3,FALSE) -> 276.6157 | M15: =VLOOKUP(J15,B69:F89,3,FALSE) -> 114.48709
B16: Inventory Turnover | C16: COGS / Inventory | D16: =365/(('Verizon Com'!C42+'Verizon Com'!C43)/'Verizon Com'!C13) -> 15.695675 | E16: =365/(('Verizon Com'!D42+'Verizon Com'!D43)/'Verizon Com'!D13) -> 15.160822 | F16: =365/(('Verizon Com'!E42+'Verizon Com'!E43)/'Verizon Com'!E13) -> 13.679104
B17: Accounts Payables turnover | C17: COGS / Accounts Payables | D17: =365/(('Verizon Com'!C42+'Verizon Com'!C43)/'Verizon Com'!I10) -> 160.62829 | E17: =365/(('Verizon Com'!D42+'Verizon Com'!D43)/'Verizon Com'!J10) -> 157.70764 | F17: =365/(('Verizon Com'!E42+'Verizon Com'!E43)/'Verizon Com'!K10) -> 155.96307 | J17: Net Profit Margin | K17: =VLOOKUP(J17,B16:F36,3,FALSE) -> 0.12427727 | L17: =VLOOKUP(J17,B44:F65,3,FALSE) -> 0.1742089 | M17: =VLOOKUP(J17,B71:F91,3,FALSE) -> 0.12447202
B18: Profitability Ratios | J18: Return on Assets (ROA) | K18: =VLOOKUP(J18,B17:F37,3,FALSE) -> 0.042482771 | L18: =VLOOKUP(J18,B45:F66,3,FALSE) -> 0.052092109 | M18: =VLOOKUP(J18,B72:F92,3,FALSE) -> 0.050137522
B19: Net Profit Margin | C19: Net_Income / Revenue | D19: ='Verizon Com'!C58/'Verizon Com'!C39 -> 0.12427727 | E19: ='Verizon Com'!D58/'Verizon Com'!D39 -> 0.12987803 | F19: ='Verizon Com'!E58/'Verizon Com'!E39 -> 0.086688462 | J19: Return on Equity (ROE) | K19: =VLOOKUP(J19,B18:F38,3,FALSE) -> 0.16241571 | L19: =VLOOKUP(J19,B46:F67,3,FALSE) -> 0.17304788 | M19: =VLOOKUP(J19,B73:F93,3,FALSE) -> 0.18566627
B20: Return on Assets (ROA) | C20: Net_Income / Total_Assets | D20: ='Verizon Com'!C58/'Verizon Com'!C27 -> 0.042482771 | E20: ='Verizon Com'!D58/'Verizon Com'!D27 -> 0.045504288 | F20: ='Verizon Com'!E58/'Verizon Com'!E27 -> 0.030542662
B21: Return on Equity (ROE) | C21: Net_Income / Shareholders_Equity | D21: ='Verizon Com'!C58/'Verizon Com'!I31 -> 0.16241571 | E21: ='Verizon Com'!D58/'Verizon Com'!J31 -> 0.17405916 | F21: ='Verizon Com'!E58/'Verizon Com'!K31 -> 0.12381795 | J21: Earnings Per Share (diluted EPS) | K21: =VLOOKUP(J21,B19:F39,3,FALSE) -> 4.0590877 | L21: =VLOOKUP(J21,B47:F68,3,FALSE) -> 3.04 | M21: =VLOOKUP(J21,B75:F95,3,FALSE) -> 9.72
B22: Market Value Ratios | J22: Stock Price as of 31 Dec 2025 | K22: =VLOOKUP(J22,B20:F40,3,FALSE) -> 40.04 | L22: =VLOOKUP(J22,B48:F69,3,FALSE) -> 24.55 | M22: =VLOOKUP(J22,B76:F96,3,FALSE) -> 202.07
B23: Earnings Per Share (diluted EPS) | D23: ='Verizon Com'!C58/'Verizon Com'!C67 -> 4.0590877 | E23: ='Verizon Com'!D58/'Verizon Com'!D67 -> 4.1453943 | F23: ='Verizon Com'!E58/'Verizon Com'!E67 -> 2.7553974 | J23: Price to Earnings (P/E) ratio | K23: =VLOOKUP(J23,B21:F41,3,FALSE) -> 9.8642855 | L23: =VLOOKUP(J23,B49:F70,3,FALSE) -> 8.0756579 | M23: =VLOOKUP(J23,B77:F97,3,FALSE) -> 20.789095
B24: Stock Price as of 31 Dec 2025 | C24: Adjusted price taken from Yahoo_finance | D24: 40.04 | E24: 36.78 | F24: 32.5 | J24: Free cash flow from operations | K24: =VLOOKUP(J24,B22:F42,3,FALSE) -> 20126 | L24: =VLOOKUP(J24,B50:F71,3,FALSE) -> 19442 | M24: =VLOOKUP(J24,B78:F98,3,FALSE) -> 17995
B25: Price to Earnings (P/E) ratio | C25: Stock_Price / EPS | D25: =D24/D23 -> 9.8642855 | E25: =E24/E23 -> 8.8724974 | F25: =F24/F23 -> 11.795032
B26: Free cash flow from operations | C26: Net Cash Provided by Operating Activities - Capital Expenditures | D26: ='Verizon Com'!I73 -> 20126 | E26: ='Verizon Com'!J73 -> 19822 | F26: ='Verizon Com'!K73 -> 18708
B31: AT&T
B32: Financial Ratios | C32: Formulas | D32: 2025 | E32: 2024 | F32: 2023
B33: Liquidity Ratios (Short-Term Solvency)
B34: Current Ratio | C34: Current_Assets / Current_Liabilities | D34: ='AT&T'!C13/'AT&T'!I13 -> 0.90613611 | E34: ='AT&T'!D13/'AT&T'!J13 -> 0.66495989 | F34: ='AT&T'!E13/'AT&T'!K13 -> 0.71308702
B35: Quick Ratio | C35: (Current_Assets - Inventory) / Current_Liabilities | D35: =('AT&T'!C13-'AT&T'!C11)/'AT&T'!I13 -> 0.86113797 | E35: =('AT&T'!D13-'AT&T'!D11)/'AT&T'!J13 -> 0.61653012 | F35: =('AT&T'!E13-'AT&T'!E11)/'AT&T'!K13 -> 0.67050678
B36: Cash Ratio | C36: Cash / Current Liabilities | D36: ='AT&T'!C9/'AT&T'!I13 -> 0.33904797 | E36: ='AT&T'!D9/'AT&T'!J13 -> 0.070361836 | F36: ='AT&T'!E9/'AT&T'!K13 -> 0.13147652
B37: Long-Term Solvency
B38: Debt to Equity Ratio | C38: Total_Liabilities / Shareholders_Equity | D38: ='AT&T'!I22/'AT&T'!I31 -> 2.3219597 | E38: ='AT&T'!J22/'AT&T'!J31 -> 2.3387881 | F38: ='AT&T'!K22/'AT&T'!K31 -> 2.4492515
B39: Debt to Assets Ratio | C39: Total_Liabilities / Total Assets | D39: ='AT&T'!I22/'AT&T'!C22 -> 0.69897287 | E39: ='AT&T'!J22/'AT&T'!D22 -> 0.70049013 | F39: ='AT&T'!K22/'AT&T'!E22 -> 0.7066403
B40: Interest Coverage | C40: Operating_Income / Interest_Expense | D40: =-'AT&T'!C50/'AT&T'!C51 -> 3.5511464 | E40: =-'AT&T'!D50/'AT&T'!D51 -> 2.8183163 | F40: =-'AT&T'!E50/'AT&T'!E51 -> 3.4995525
B41: Efficiency Ratios
B42: Total Asset Turnover | C42: Revenue / Total_Assets | D42: ='AT&T'!C39/'AT&T'!C22 -> 0.29902094 | E42: ='AT&T'!D39/'AT&T'!D22 -> 0.30987221 | F42: ='AT&T'!E39/'AT&T'!E22 -> 0.30076156
B43: Accounts Receivables Turnover | C43: Revenue / Accounts_Receivable | D43: =365/('AT&T'!C39/'AT&T'!C10) -> 25.688391 | E43: =365/('AT&T'!D39/'AT&T'!D10) -> 28.755804 | F43: =365/('AT&T'!E39/'AT&T'!E10) -> 30.67505
B44: Inventory Turnover | C44: COGS / Inventory | D44: =365/(('AT&T'!C43+'AT&T'!C44)/'AT&T'!C11) -> 17.380952 | E44: =365/(('AT&T'!D43+'AT&T'!D44)/'AT&T'!D11) -> 16.833262 | F44: =365/(('AT&T'!E43+'AT&T'!E44)/'AT&T'!E11) -> 15.853101
B45: Accounts Payables turnover | C45: COGS / Accounts Payables | D45: =365/(('AT&T'!C43+'AT&T'!C44)/'AT&T'!I10) -> 276.6157 | E45: =365/(('AT&T'!D43+'AT&T'!D44)/'AT&T'!J10) -> 264.4157 | F45: =365/(('AT&T'!E43+'AT&T'!E44)/'AT&T'!K10) -> 261.07735
B46: Profitability Ratios
B47: Net Profit Margin | C47: Net_Income / Revenue | D47: ='AT&T'!C63/'AT&T'!C39 -> 0.1742089 | E47: ='AT&T'!D63/'AT&T'!D39 -> 0.087840047 | F47: ='AT&T'!E63/'AT&T'!E39 -> 0.11592119
B48: Return on Assets (ROA) | C48: Net_Income / Total_Assets | D48: ='AT&T'!C63/'AT&T'!C22 -> 0.052092109 | E48: ='AT&T'!D63/'AT&T'!D22 -> 0.02721919 | F48: ='AT&T'!E63/'AT&T'!E22 -> 0.034864639
B49: Return on Equity (ROE) | C49: Net_Income / Shareholders_Equity | D49: ='AT&T'!C63/'AT&T'!I31 -> 0.17304788 | E49: ='AT&T'!D63/'AT&T'!J31 -> 0.090879107 | F49: ='AT&T'!E63/'AT&T'!K31 -> 0.12084263
B50: Market Value Ratios
B51: Earnings Per Share (diluted EPS) | D51: ='AT&T'!C67 -> 3.04 | E51: ='AT&T'!D67 -> 1.49 | F51: ='AT&T'!E67 -> 1.97
B52: Stock Price as of 31 Dec 2025 | C52: Adjusted price taken from Yahoo_finance | D52: 24.55 | E52: 21.54 | F52: 14.95
B53: Price to Earnings (P/E) ratio | C53: Stock_Price / EPS | D53: =D52/D51 -> 8.0756579 | E53: =E52/E51 -> 14.456376 | F53: =F52/F51 -> 7.5888325
B55: Free cash flow from operations | C55: Net Cash Provided by Operating Activities - Capital Expenditures | D55: ='AT&T'!I92 -> 19442 | E55: ='AT&T'!J92 -> 18508 | F55: ='AT&T'!K92 -> 20461
B57: T-mobile
B58: Financial Ratios | C58: Formulas | D58: 2025 | E58: 2024 | F58: 2023
B59: Liquidity Ratios (Short-Term Solvency)
B60: Current Ratio | C60: Current_Assets / Current_Liabilities | D60: ='T-mobile'!C15/'T-mobile'!I15 -> 0.99840816 | E60: ='T-mobile'!D15/'T-mobile'!J15 -> 0.91226331 | F60: ='T-mobile'!E15/'T-mobile'!K15 -> 0.90859136
B61: Quick Ratio | C61: (Current_Assets - Inventory) / Current_Liabilities | D61: =('T-mobile'!C15-'T-mobile'!C12)/'T-mobile'!I15 -> 0.9002449 | E61: =('T-mobile'!D15-'T-mobile'!D12)/'T-mobile'!J15 -> 0.83260632 | F61: =('T-mobile'!E15-'T-mobile'!E12)/'T-mobile'!K15 -> 0.8284117
B62: Cash Ratio | C62: Cash / Current Liabilities | D62: ='T-mobile'!C9/'T-mobile'!I15 -> 0.2284898 | E62: ='T-mobile'!D9/'T-mobile'!J15 -> 0.26811738 | F62: ='T-mobile'!E9/'T-mobile'!K15 -> 0.24536506
B63: Long-Term Solvency
B64: Debt to Equity Ratio | C64: Total_Liabilities / Shareholders_Equity | D64: ='T-mobile'!I24/'T-mobile'!I33 -> 2.70314 | E64: ='T-mobile'!J24/'T-mobile'!J33 -> 2.369479 | F64: ='T-mobile'!K24/'T-mobile'!K33 -> 2.2091787
B65: Debt to Assets Ratio | C65: Total_Liabilities / Total Assets | D65: ='T-mobile'!I24/'T-mobile'!C25 -> 0.7299589 | E65: ='T-mobile'!J24/'T-mobile'!D25 -> 0.70321821 | F65: ='T-mobile'!K24/'T-mobile'!E25 -> 0.68839379
B66: Interest Coverage | C66: Operating_Income / Interest_Expense | D66: =-'T-mobile'!C55/'T-mobile'!C57 -> 4.8434022 | E66: =-'T-mobile'!D55/'T-mobile'!D57 -> 5.2799765 | F66: =-'T-mobile'!E55/'T-mobile'!E57 -> 4.2776612
B67: Efficiency Ratios
B68: Total Asset Turnover | C68: Revenue / Total_Assets | D68: ='T-mobile'!C45/'T-mobile'!C25 -> 0.40280153 | E68: ='T-mobile'!D45/'T-mobile'!D25 -> 0.39128031 | F68: ='T-mobile'!E45/'T-mobile'!E25 -> 0.378261
B69: Accounts Receivables Turnover | C69: Revenue / Accounts_Receivable | D69: =365/('T-mobile'!C45/'T-mobile'!C10) -> 20.145285 | E69: =365/('T-mobile'!D45/'T-mobile'!D10) -> 19.17371 | F69: =365/('T-mobile'!E45/'T-mobile'!E10) -> 21.800199
B70: Inventory Turnover | C70: COGS / Inventory | D70: =365/(('T-mobile'!C48+'T-mobile'!C49)/'T-mobile'!C12) -> 26.784189 | E70: =365/(('T-mobile'!D48+'T-mobile'!D49)/'T-mobile'!D12) -> 19.780629 | F70: =365/(('T-mobile'!E48+'T-mobile'!E49)/'T-mobile'!E12) -> 20.288525
B71: Accounts Payables turnover | C71: COGS / Accounts Payables | D71: =365/(('T-mobile'!C48+'T-mobile'!C49)/'T-mobile'!I9) -> 114.48709 | E71: =365/(('T-mobile'!D48+'T-mobile'!D49)/'T-mobile'!J9) -> 104.17142 | F71: =365/(('T-mobile'!E48+'T-mobile'!E49)/'T-mobile'!K9) -> 125.41888
B72: Profitability Ratios
B73: Net Profit Margin | C73: Net_Income / Revenue | D73: ='T-mobile'!C62/'T-mobile'!C45 -> 0.12447202 | E73: ='T-mobile'!D62/'T-mobile'!D45 -> 0.13929975 | F73: ='T-mobile'!E62/'T-mobile'!E45 -> 0.10587082
B74: Return on Assets (ROA) | C74: Net_Income / Total_Assets | D74: ='T-mobile'!C62/'T-mobile'!C25 -> 0.050137522 | E74: ='T-mobile'!D62/'T-mobile'!D25 -> 0.054505252 | F74: ='T-mobile'!E62/'T-mobile'!E25 -> 0.040046802
B75: Return on Equity (ROE) | C75: Net_Income / Shareholders_Equity | D75: ='T-mobile'!C62/'T-mobile'!I33 -> 0.18566627 | E75: ='T-mobile'!D62/'T-mobile'!J33 -> 0.1836543 | F75: ='T-mobile'!E62/'T-mobile'!K33 -> 0.12851735
B76: Market Value Ratios
B77: Earnings Per Share (diluted EPS) | D77: ='T-mobile'!C80 -> 9.72 | E77: ='T-mobile'!D80 -> 9.66 | F77: ='T-mobile'!E80 -> 6.93
B78: Stock Price as of 31 Dec 2025 | C78: Adjusted price taken from Yahoo_finance | D78: 202.07 | E78: 216.3 | F78: 154.83
B79: Price to Earnings (P/E) ratio | C79: Stock_Price / EPS | D79: =D78/D77 -> 20.789095 | E79: =E78/E77 -> 22.391304 | F79: =F78/F77 -> 22.341991
B81: Free cash flow from operations | C81: Net Cash Provided by Operating Activities - Capital Expenditures | D81: ='T-mobile'!I98 -> 17995 | E81: ='T-mobile'!J98 -> 13453 | F81: ='T-mobile'!K98 -> 8758

Sheet Financial Ratios Dashboard

Sheet WACC -  Verizon
B1: RAVSHANBEK MAMASAIDOV
B3: Verizon Communications Inc. and Subsidiaries
B4: Inputs | C4: Value | D4: Description | E4: Source
B5: Beta | C5: =Beta!K13 -> 0.30175917 | D5: estimated using past 5 year price data | E5: =HYPERLINK("https://finance.yahoo.com/quote/VZ/","Stock Quote Link") -> Stock Quote Link
B6: Risk Free Rate (Rf) | C6: =CAPM!H16 -> 0.0405 | D6: U.S. 10-year Treasury Yield (as of 03/02/2026) | E6: =HYPERLINK("https://home.treasury.gov/resource-center/data-chart-center/interest-rates/TextView?type=daily_treasury_yield_curve&field_tdr_date_value=202602 ","Risk Free Rate Link") -> Risk Free Rate Link
B7: Market Return (MR) | C7: ='Market Return'!G10 -> 0.12755429 | D7: estimated using past 5 year S&P annual return from macrotrends.net | E7: =HYPERLINK("https://www.macrotrends.net/2526/sp-500-historical-annual-returns ","Macrotrends") -> Macrotrends
B8: Stock price (P0) | C8: =DDM!K7 -> 49.98 | D8: Price as of 03/01/2026 from Finance Yahoo | E8: =HYPERLINK("https://finance.yahoo.com/quote/VZ/","Stock Quote Link") -> Stock Quote Link
B9: Growth rate (g) | C9: =DDM!K9 -> 0.022831331 | D9: estimated using past 5 year dividends
B10: Dividend | C10: 0.7075 | D10: Most recent dividend for Verizon (D0) | E10: Verizon official website
B12: CAPM (Re) | C12: =C6+C5*(C7-C6) -> 0.06676943 | D12: Cost of equity using CAPM: Rf + Beta*(MR - Rf)
B13: DDM (Re) | C13: =C10*(1+C9)/C8+C9 -> 0.037310186 | D13: Cost of equity using DDM: RE=D0*(1+g)/P0 + g
B14: Shares outstanding: | C14: =4236*1000000 -> 4236000000 | D14: Total number of shares, from Finance Yahoo as of 1 March 2026 | E14: =HYPERLINK("https://www.macrotrends.net/stocks/charts/VZ/verizon/shares-outstanding ","Macrotrends") -> Macrotrends
B16: Total Market Value of Equity | C16: =C14*C8 -> 211715280000 | D16: Total Market Value of Equity
B17: Cost of Equity | C17: =(C12+C13)/2 -> 0.052039808 | D17: cost of equity taken from average of CAPM and DDM
B19: Pretax Cost of Debt | C19: ='Cost of Debt'!H62 -> 0.04522411
B20: Tax Rate | C20: 0.21 | D20: Corporate Tax Rate
B21: Aftertax Cost of Debt | C21: =C19*(1-C20) -> 0.035727047
B22: Total Market Value of Debt | C22: ='Cost of Debt'!F62 -> 177789842930
B24: Weight of Debt | C24: =C22/(C22+C16) -> 0.45645059 | D24: MV of Debt / (MV of Debt + MV of Equity)
B25: Weight of Equity | C25: =C16/(C22+C16) -> 0.54354941 | D25: MV of Equity / (MV of Debt + MV of Equity)
B26: WACC | C26: =(C17*C25)+(C19*(1-C20)*C24) -> 0.044593839 | D26: (Cost of Equity*Weight of Equity)+(Cost of Debt*(1-Tax Rate)*Weight of Debt)

Sheet Beta
B1: Beta was estimated using five years of adjusted closing prices from Yahoo Finance. Returns were calculated for both the stock and the S&P 500, and the relationship between them was analyzed in Excel to measure the stock’s sensitivity to market movements.
B5: Date | C5: Verizon | D5: Return cost | E5: S&P 500 | F5: Return cost
B6: 44256 | C6: 42.81 | E6: 3972.89
B7: 44287 | C7: 42.55 | D7: =(C7-C6)/C6 -> -0.0060733473 | E7: 4181.17 | F7: =(E7-E6)/E6 -> 0.052425313 | I7: Cov(RCOST,RSP) | K7: =_xlfn.COVARIANCE.P(D7:D66,F7:F66) -> 0.0005617524
B8: 44317 | C8: 42.04 | D8: =(C8-C7)/C7 -> -0.011985899 | E8: 4204.11 | F8: =(E8-E7)/E7 -> 0.0054865026
B9: 44348 | C9: 41.7 | D9: =(C9-C8)/C8 -> -0.0080875357 | E9: 4297.5 | F9: =(E9-E8)/E8 -> 0.022213976
B10: 44378 | C10: 41.51 | D10: =(C10-C9)/C9 -> -0.0045563549 | E10: 4395.26 | F10: =(E10-E9)/E9 -> 0.022748109 | I10: Var(RSP) | K10: =_xlfn.VAR.P(F7:F66) -> 0.0018615918
B11: 44409 | C11: 41.39 | D11: =(C11-C10)/C10 -> -0.0028908697 | E11: 4522.68 | F11: =(E11-E10)/E10 -> 0.028990321
B12: 44440 | C12: 40.65 | D12: =(C12-C11)/C11 -> -0.017878715 | E12: 4307.54 | F12: =(E12-E11)/E11 -> -0.04756914
B13: 44470 | C13: 39.88 | D13: =(C13-C12)/C12 -> -0.018942189 | E13: 4605.38 | F13: =(E13-E12)/E12 -> 0.069143873 | I13: βCOST | K13: =K7/K10 -> 0.30175917
B14: 44501 | C14: 38.28 | D14: =(C14-C13)/C13 -> -0.040120361 | E14: 4567 | F14: =(E14-E13)/E13 -> -0.0083337314
B15: 44531 | C15: 39.57 | D15: =(C15-C14)/C14 -> 0.03369906 | E15: 4766.18 | F15: =(E15-E14)/E14 -> 0.043612875
B16: 44562 | C16: 40.53 | D16: =(C16-C15)/C15 -> 0.024260804 | E16: 4515.55 | F16: =(E16-E15)/E15 -> -0.052585089
B17: 44593 | C17: 41.36 | D17: =(C17-C16)/C16 -> 0.020478658 | E17: 4373.94 | F17: =(E17-E16)/E16 -> -0.031360521
B18: 44621 | C18: 39.26 | D18: =(C18-C17)/C17 -> -0.050773694 | E18: 4530.41 | F18: =(E18-E17)/E17 -> 0.035773239
B19: 44652 | C19: 35.68 | D19: =(C19-C18)/C18 -> -0.091186959 | E19: 4131.93 | F19: =(E19-E18)/E18 -> -0.087956719
B20: 44682 | C20: 40.01 | D20: =(C20-C19)/C19 -> 0.1213565 | E20: 4132.15 | F20: =(E20-E19)/E19 -> 5.3243884e-05
B21: 44713 | C21: 39.59 | D21: =(C21-C20)/C20 -> -0.010497376 | E21: 3785.38 | F21: =(E21-E20)/E20 -> -0.083919993
B22: 44743 | C22: 36.03 | D22: =(C22-C21)/C21 -> -0.089921697 | E22: 4130.29 | F22: =(E22-E21)/E21 -> 0.091116348
B23: 44774 | C23: 33.02 | D23: =(C23-C22)/C22 -> -0.083541493 | E23: 3955 | F23: =(E23-E22)/E22 -> -0.042440119
B24: 44805 | C24: 29.99 | D24: =(C24-C23)/C23 -> -0.091762568 | E24: 3585.62 | F24: =(E24-E23)/E23 -> -0.093395702
B25: 44835 | C25: 29.52 | D25: =(C25-C24)/C24 -> -0.015671891 | E25: 3871.98 | F25: =(E25-E24)/E24 -> 0.079863455
... B66: 46082 | C66: 49.98 | D66: =(C66-C65)/C65 -> -0.003191065 | E66: 6716.09 | F66: =(E66-E65)/E65 -> -0.02366519

Sheet Market Return
B1: We use S&P 500 index annual return as proxy for market return.
B2: 1. First we're going to collect the data from | E2: macrotrends.net.
B3: 2. Calculate the arithmetic average annual return and geometric average annual return.
B5: Date | C5: S&P 500 Annual Return
B6: 10593 | C6: 0.3788
B7: 10958 | C7: -0.1191 | F7: Last 5 Year Arithmetic Annual return | G7: =AVERAGE(C99:C103) -> 0.14276
B8: 11323 | C8: -0.2848
B9: 11688 | C9: -0.4707
B10: 12054 | C10: -0.1515 | F10: Last 5 Year Geometric Annual Return | G10: {=PRODUCT(1+C99:C103)^(1/5)-1} -> 0.12755429
B11: 12419 | C11: 0.4659
B12: 12784 | C12: -0.0594
B13: 13149 | C13: 0.4137
B14: 13515 | C14: 0.2792
B15: 13880 | C15: -0.3859
B16: 14245 | C16: 0.2521
B17: 14610 | C17: -0.0545
B18: 14976 | C18: -0.1529
B19: 15341 | C19: -0.1786
B20: 15706 | C20: 0.1243
B21: 16071 | C21: 0.1945
B22: 16437 | C22: 0.138
... B103: 46022 | C103: 0.1639

Sheet CAPM
C1: For CAPM and WACC modules
C2: We used 10-year Treasury yield
C3: 2nd March 2026 taken, since it is closest to 1 March 2026 where initial calculations are being made.
C5: Risk free rate taken from | F5: https://home.treasury.gov/resource-center/data-chart-center/interest-rates/TextView?type=daily_treasury_yield_curve&field_tdr_date_value=202602
C6: Date | D6: 1 Mo | E6: 1.5 Month | F6: 2 Mo | G6: 3 Mo | H6: 4 Mo | I6: 6 Mo | J6: 1 Yr | K6: 2 Yr | L6: 3 Yr | M6: 5 Yr | N6: 7 Yr | O6: 10 Yr | P6: 20 Yr | Q6: 30 Yr
C7: 03/05/2026 | D7: 3.75 | E7: 3.74 | F7: 3.72 | G7: 3.7 | H7: 3.68 | I7: 3.68 | J7: 3.59 | K7: 3.57 | L7: 3.59 | M7: 3.72 | N7: 3.92 | O7: 4.13 | P7: 4.71 | Q7: 4.74
C8: 03/04/2026 | D8: 3.75 | E8: 3.75 | F8: 3.75 | G8: 3.71 | H8: 3.68 | I8: 3.68 | J8: 3.58 | K8: 3.54 | L8: 3.55 | M8: 3.67 | N8: 3.87 | O8: 4.09 | P8: 4.67 | Q8: 4.72
C9: 03/03/2026 | D9: 3.75 | E9: 3.75 | F9: 3.74 | G9: 3.71 | H9: 3.67 | I9: 3.68 | J9: 3.55 | K9: 3.51 | L9: 3.5 | M9: 3.63 | N9: 3.83 | O9: 4.06 | P9: 4.65 | Q9: 4.7
C10: 03/02/2026 | D10: 3.74 | E10: 3.74 | F10: 3.74 | G10: 3.72 | H10: 3.68 | I10: 3.68 | J10: 3.54 | K10: 3.47 | L10: 3.49 | M10: 3.62 | N10: 3.82 | O10: 4.05 | P10: 4.64 | Q10: 4.7
C11: 02/27/2026 | D11: 3.74 | E11: 3.73 | F11: 3.73 | G11: 3.67 | H11: 3.67 | I11: 3.6 | J11: 3.48 | K11: 3.38 | L11: 3.39 | M11: 3.51 | N11: 3.72 | O11: 3.97 | P11: 4.57 | Q11: 4.64
C12: 02/26/2026 | D12: 3.74 | E12: 3.74 | F12: 3.75 | G12: 3.68 | H12: 3.68 | I12: 3.61 | J12: 3.52 | K12: 3.42 | L12: 3.46 | M12: 3.57 | N12: 3.78 | O12: 4.02 | P12: 4.6 | Q12: 4.67
C13: 02/25/2026 | D13: 3.71 | E13: 3.74 | F13: 3.73 | G13: 3.69 | H13: 3.68 | I13: 3.62 | J13: 3.53 | K13: 3.45 | L13: 3.49 | M13: 3.61 | N13: 3.82 | O13: 4.05 | P13: 4.63 | Q13: 4.7
C14: 02/24/2026 | D14: 3.72 | E14: 3.75 | F14: 3.73 | G14: 3.69 | H14: 3.7 | I14: 3.62 | J14: 3.52 | K14: 3.43 | L14: 3.47 | M14: 3.61 | N14: 3.81 | O14: 4.04 | P14: 4.63 | Q14: 4.7
C16: Rf, we are using 10 year rate | H16: 0.0405
C17: E(RM), we are using 5 year geometric average | H17: ='Market Return'!G10 -> 0.12755429
C18: Beta (β) | H18: =Beta!K13 -> 0.30175917
C19: Cost of equity for Verizon using CAPM: E(Re)=Rf+ βi∗[E(Rm )−Rf ]
C20: Cost of equity E(Re) | H20: =H16+H18*(H17-H16) -> 0.06676943 | I20: return investors require

Sheet DDM
B2: Verizon Communications Inc. Common Stock (VZ) Dividend History
B3: Interval: | C3: 6 years
B4: Source: | C4: Verizon official website
B5: Purpose to find | C5: Growth rate and Cost of Equity
B7: Ex-Dividend Date | C7: Cash Amount | E7: Year | F7: CASH AMOUNT | G7: ANNUAL GROWTH RATE | I7: Market close price as of 03/01/2026 | K7: =Beta!C66 -> 49.98
B8: 46122 | C8: 0.7075 | E8: 2026 | F8: =C8 -> 0.7075 | G8: =(F8-F9)/F9 -> 0.044280443 | I8: Most recent dividend for Verizon (D0) | K8: 0.7075
B9: 46034 | C9: 0.69 | E9: 2025 | F9: =C11 -> 0.6775 | G9: =(F9-F10)/F10 -> 0.018796992 | I9: Estimated growth rate for dividends | K9: =G15 -> 0.022831331
B10: 45940 | C10: 0.69 | E10: 2024 | F10: =C15 -> 0.665 | G10: =(F10-F11)/F11 -> 0.019157088 | I10: Dividend 1 (future/next) | K10: =K8*(1+K9) -> 0.72365317
B11: 45848 | C11: 0.6775 | E11: 2023 | F11: =C19 -> 0.6525 | G11: =(F11-F12)/F12 -> 0.01953125
B12: 45757 | C12: 0.6775 | E12: 2022 | F12: =C23 -> 0.64 | G12: =(F12-F13)/F13 -> 0.019920319 | I12: Cost of equity using DDM: RE=D0*(1+g)/P0 + g | K12: =K10/K7+K9 -> 0.037310186
B13: 45667 | C13: 0.6775 | E13: 2021 | F13: =C27 -> 0.6275
B14: 45575 | C14: 0.6775 | E14: Last 5 Year Growth
B15: 45483 | C15: 0.665 | G15: =GEOMEAN(G8:G12) -> 0.022831331
B16: 45391 | C16: 0.665
B17: 45300 | C17: 0.665
B18: 45205 | C18: 0.665
B19: 45114 | C19: 0.6525
B20: 45022 | C20: 0.6525
B21: 44935 | C21: 0.6525
B22: 44840 | C22: 0.6525
B23: 44749 | C23: 0.64
B24: 44658 | C24: 0.64
B25: 44568 | C25: 0.64
B26: 44476 | C26: 0.64
B27: 07-08-2021 | C27: 0.6275
B28: 04-08-2021 | C28: 0.6275
B29: 01-07-2021 | C29: 0.6275
B30: 10-08-2020 | C30: 0.6275
B31: 07-09-2020 | C31: 0.615
B32: 04-09-2020 | C32: 0.615

Sheet Cost of Debt
A1: Verizon`s Cost of Debt
A2: To find the cost of debt, we need the current YTM of the company's bonds, the bond price, and the book value of the bonds. The YTM and price are found on the FINRA bond website, while the book value is found in the company's 10-K or 10-Q. While the SEC website has the most recent electronic filing, the hyperlink below still requires the user to find the most recent report and look up the information.
A3: =HYPERLINK("https://www.finra.org/finra-data/fixed-income/corp-and-agency","FINRA bond quote") -> FINRA bond quote
A4: =HYPERLINK("https://www.sec.gov/edgar/browse/?CIK=732712&owner=exclude","SEC EDGAR database") -> SEC EDGAR database
A6: The Market-Based Method (Preferred)
A7: Bond price and yield information for Verizon from FINRA.org
A8: 7 Notes/Bonds taken with various maturities "<5, 5-10, and >10" years
B10: Symbol | C10: Issuer Name | D10: Coupon rate | E10: Maturity Date | F10: Maturity | G10: Latest Sale Price | H10: Sale Yield
B11: VZ4388863 | C11: VERIZON COMMUNICATIONS INC | D11: 2.625 | E11: 46249 | F11: <5 years | G11: 97.896 | H11: 4.28
B12: VZ4648231 | C12: VERIZON COMMUNICATIONS INC | D12: 4.329 | E12: 47017 | F12: <5 years | G12: 116.586 | H12: 2.19
B13: VZ4804253 | C13: VERIZON COMMUNICATIONS INC | D13: 4.016 | E13: 47455 | F13: <5 years | G13: 94.462 | H13: 5.32
B14: VZ4632280 | C14: VERIZON COMMUNICATIONS INC | D14: 4.05 | E14: 47618 | F14: <5 years | G14: 100.557 | H14: 0.94
B15: VZ5252608 | C15: VERIZON COMMUNICATIONS INC | D15: 2.355 | E15: 48288 | F15: 5-10 years | G15: 87.62 | H15: 4.71
B16: VZ4106368 | C16: VERIZON COMMUNICATIONS INC | D16: 5.05 | E16: 49018 | F16: 5-10 years | G16: 101.246 | H16: 4.85
B17: VZ.RX | C17: VERIZON COMMUNICATIONS INC | D17: 8.95 | E17: 50830 | F17: >10 years | G17: 132.11 | H17: 5.45
A19: Bond book value from Verizon 10Q on sec.gov
L22: Total bonds <5 years debt | M22: =(29192+1373+38+317+18247+8857)*1000000 -> 58024000000
L23: Total bonds 5-10 years debt | M23: =(39769+647+56+297)*1000000 -> 40769000000
L24: Total bonds >10years debt | M24: =60471*1000000 -> 60471000000
B53: Maturity | C53: Maturity date | D53: YTM | E53: Quoted Price | F53: Book Value | G53: Market Value | H53: Market Value Weight | I53: Weight×YTM
B54: <5 years | C54: 2026 | D54: =H11/100 -> 0.0428 | E54: =G11 -> 97.896 | F54: =$M$22/4 -> 14506000000 | G54: =E54/100*F54 -> 14200793760 | H54: =G54/$F$62 -> 0.079874044 | I54: =H54*D54 -> 0.0034186091
B55: <5 years | C55: 2028 | D55: =H12/100 -> 0.0219 | E55: =G12 -> 116.586 | F55: =$M$22/4 -> 14506000000 | G55: =E55/100*F55 -> 1.6911965e+10 | H55: =G55/$F$62 -> 0.095123348 | I55: =H55*D55 -> 0.0020832013
B56: <5 years | C56: 2029 | D56: =H13/100 -> 0.0532 | E56: =G13 -> 94.462 | F56: =$M$22/4 -> 14506000000 | G56: =E56/100*F56 -> 13702657720 | H56: =G56/$F$62 -> 0.077072219 | I56: =H56*D56 -> 0.0041002421
B57: <5 years | C57: 2030 | D57: =H14/100 -> 0.0094 | E57: =G14 -> 100.557 | F57: =$M$22/4 -> 14506000000 | G57: =E57/100*F57 -> 1.4586798e+10 | H57: =G57/$F$62 -> 0.082045173 | I57: =H57*D57 -> 0.00077122463
B58: 5-10 years | C58: 2032 | D58: =H15/100 -> 0.0471 | E58: =G15 -> 87.62 | F58: =$M$23/2 -> 20384500000 | G58: =E58/100*F58 -> 17860898900 | H58: =G58/$F$62 -> 0.10046074 | I58: =H58*D58 -> 0.0047317008
B59: 5-10 years | C59: 2034 | D59: =H16/100 -> 0.0485 | E59: =G16 -> 101.246 | F59: =$M$23/2 -> 20384500000 | G59: =E59/100*F59 -> 20638490870 | H59: =G59/$F$62 -> 0.11608363 | I59: =H59*D59 -> 0.0056300562
B60: >10 years | C60: 2039 | D60: =5.45/100 -> 0.0545 | E60: =G17 -> 132.11 | F60: =M24 -> 60471000000 | G60: =E60/100*F60 -> 7.9888238e+10 | H60: =G60/$F$62 -> 0.44934084 | I60: =H60*D60 -> 0.024489076
D62: Total market value = | F62: =SUM(G54:G60) -> 177789842930 | G62: Cost of debt before tax = | H62: =SUM(I54:I60) -> 0.04522411
B64: Tax rate: | D64: 0.21
B65: Aftertax cost of debt: | D65: =H62*(1-D64) -> 0.035727047
B67: Verizon's Cost of Preferred Stock
B68: By reading through Verizon's most recent 10-Q, Verizon has no preferred stock shares outstanding
